MANIFEST.in
README.rst
setup.py
linkedin/__init__.py
linkedin/exceptions.py
linkedin/linkedin.py
linkedin/models.py
linkedin/server.py
linkedin/utils.py
linkedin_sdk.egg-info/PKG-INFO
linkedin_sdk.egg-info/SOURCES.txt
linkedin_sdk.egg-info/dependency_links.txt
linkedin_sdk.egg-info/not-zip-safe
linkedin_sdk.egg-info/requires.txt
linkedin_sdk.egg-info/top_level.txt