Metadata-Version: 1.2
Name: linkedin-sdk
Version: 0.0.2
Summary: Python Interface to the LinkedIn API
Home-page: https://github.com/c0mpiler/linkedin-sdk
Author: Harsha Krishnareddy
Author-email: harsha@ins8s.com
Maintainer: Harsha Krishnareddy
Maintainer-email: harsha@ins8s.com
License: Apache
Keywords: linkedin python python3
Platform: UNKNOWN
Classifier: Development Status :: 5 - Production/Stable
Classifier: Environment :: Console
Classifier: Intended Audience :: Developers
Classifier: License :: OSI Approved :: MIT License
Classifier: Operating System :: OS Independent
Classifier: Programming Language :: Python :: 3
Classifier: Programming Language :: Python :: 3.4
Classifier: Programming Language :: Python :: 3.5
Classifier: Programming Language :: Python :: 3.6
Classifier: Programming Language :: Python :: 3.7
Classifier: Natural Language :: English
